csv_test_package/__init__.py
csv_test_package/compare.py
csv_test_package/csvfile.py
csv_test_package/exceptions.py
csv_test_package/utils.py
csv_test_package-0.1.6.dist-info/LICENSE
csv_test_package-0.1.6.dist-info/METADATA
csv_test_package-0.1.6.dist-info/WHEEL
csv_test_package-0.1.6.dist-info/RECORD
