Metadata-Version: 2.1
Name: csv_test_package
Version: 0.1.6
Summary: A Python package for comparing CSV files
Author: Wassim SASSI
Author-email: wassim.sassi.ws@gmail.com
Requires-Python: >=3.11,<4.0
Classifier: Programming Language :: Python :: 3
Classifier: Programming Language :: Python :: 3.11
Classifier: Programming Language :: Python :: 3.12
Requires-Dist: pandas (>=2.2.1,<3.0.0)
